{
    "1": "Der Ozean besteht hauptsächlich aus Wasser",
    "2": "'auserdem' schreibt man mit scharfem s",
    "3": "Bielefeld existiert (vielleicht)",
    "4": "Dieser Text wurde von mir geschrieben",
    "5": "Ich bin tatsächlich kein gutes Weihnachtsgeschenk",
    "6": "Dieser Satz ist gelogen",
    "7": "Heute ist NICHT der 8. Dezember",
    "8": "Heute ist Montag",
    "9": "Dieser Text ist in einer JSON-Datei gespeichert",
    "10": "In 14 Tagen ist Weihnachten",
    "11": "Du kannst jetzt schon die Texte für alle anderen Tage hier einsehen. Ich sag dir aber nicht, wie",
    "12": "Vierundzwanzig dividiert durch Zwei ergibt Zwölf",
    "13": "Fische können nicht ertrinken",
    "14": "Die nächste Nintendo Direct findet frühestens morgen statt",
    "15": "'<Text hier einfügen>' ist kein kreativer Text",
    "16": "Die Wurzel aus 16 ist nicht Fünf, sondern Fünf durch Fünf mal Vier",
    "17": "Dieser Fakt wurde am 17. Oktober 2025 um 17:14 geschrieben",
    "18": "Acht mal Zehn ist nicht Achtzahn oh wait ich habe mich verschrieben lolremre",
    "19": "neunzehn neunzehn neunzehn neunzehn neunzehn neunzehn",
    "20": "''20'': ''''",
    "21": "Dieser Text steht in Zeile 22 der Datei 'fact.json'",
    "22": "Ich habe heute unter Umständen nicht.",
    "23": "Du liest diesen Satz, ohne aktiv daran zu denken, diesen Satz lesen zu wollen",
    "24": "Heute ist Weihnachten. schockierend."
}